practicuscore/addon_helper.cpython-310-x86_64-linux-gnu.so
practicuscore/api_manager.cpython-310-x86_64-linux-gnu.so
practicuscore/app_helper.cpython-310-x86_64-linux-gnu.so
practicuscore/app_host_client.cpython-310-x86_64-linux-gnu.so
practicuscore/cli.cpython-310-x86_64-linux-gnu.so
practicuscore/cloud_def.cpython-310-x86_64-linux-gnu.so
practicuscore/cloud_node.cpython-310-x86_64-linux-gnu.so
practicuscore/conf_center.cpython-310-x86_64-linux-gnu.so
practicuscore/config_def.cpython-310-x86_64-linux-gnu.so
practicuscore/conn_helper.cpython-310-x86_64-linux-gnu.so
practicuscore/container_helper.cpython-310-x86_64-linux-gnu.so
practicuscore/core_conf.cpython-310-x86_64-linux-gnu.so
practicuscore/core_context.cpython-310-x86_64-linux-gnu.so
practicuscore/core_def.cpython-310-x86_64-linux-gnu.so
practicuscore/dataprep.cpython-310-x86_64-linux-gnu.so
practicuscore/dataprep2.cpython-310-x86_64-linux-gnu.so
practicuscore/db_helper.cpython-310-x86_64-linux-gnu.so
practicuscore/defined_conn.cpython-310-x86_64-linux-gnu.so
practicuscore/dist_job.cpython-310-x86_64-linux-gnu.so
practicuscore/engine_helper.cpython-310-x86_64-linux-gnu.so
practicuscore/exceptions.cpython-310-x86_64-linux-gnu.so
practicuscore/experiment_helper.cpython-310-x86_64-linux-gnu.so
practicuscore/file_transfer_handler.cpython-310-x86_64-linux-gnu.so
practicuscore/file_transfer_mgr.cpython-310-x86_64-linux-gnu.so
practicuscore/gen_ai.cpython-310-x86_64-linux-gnu.so
practicuscore/git_helper.cpython-310-x86_64-linux-gnu.so
practicuscore/k8s_console_client.cpython-310-x86_64-linux-gnu.so
practicuscore/local_file.cpython-310-x86_64-linux-gnu.so
practicuscore/local_file_meta_tree.cpython-310-x86_64-linux-gnu.so
practicuscore/log_manager.cpython-310-x86_64-linux-gnu.so
practicuscore/mcp_helper.cpython-310-x86_64-linux-gnu.so
practicuscore/metadata_helper.cpython-310-x86_64-linux-gnu.so
practicuscore/model_conf_parser.cpython-310-x86_64-linux-gnu.so
practicuscore-25.5.2.dist-info/METADATA
practicuscore-25.5.2.dist-info/WHEEL
practicuscore-25.5.2.dist-info/entry_points.txt
practicuscore-25.5.2.dist-info/top_level.txt
practicuscore-25.5.2.dist-info/RECORD
