Metadata-Version: 2.4
Name: practicuscore
Version: 25.5.2
Summary: Practicus AI core library is the SDK that offers programmatic access for Practicus AI platform
Home-page: https://practicus.ai/
Author: Practicus AI LLC
Author-email: info@practicus.ai
Requires-Python: >=3.10
Requires-Dist: pandas
Requires-Dist: requests
Requires-Dist: websocket-client
Requires-Dist: lz4
Requires-Dist: pyOpenSSL
Requires-Dist: chardet
Requires-Dist: PyJWT[crypto]
Requires-Dist: packaging
Requires-Dist: cryptography
Requires-Dist: certifi
Requires-Dist: argcomplete
Requires-Dist: truststore
Requires-Dist: pydantic>2
Dynamic: author
Dynamic: author-email
Dynamic: description
Dynamic: description-content-type
Dynamic: home-page
Dynamic: requires-dist
Dynamic: requires-python
Dynamic: summary
